{
    "mobileBottomRow": 5,
    "widgetName": "formName",
    "dynamicPropertyPathList": [{"key": "fontSize"}],
    "displayName": "Text",
    "iconSVG": "https://appcdn.appsmith.com/static/media/icon.a47d6d5dbbb718c4dc4b2eb4f218c1b7.svg",
    "searchTags": [
        "typography",
        "paragraph",
        "label"
    ],
    "topRow": 0,
    "bottomRow": 5,
    "parentRowSpace": 10,
    "type": "TEXT_WIDGET",
    "hideCard": false,
    "mobileRightColumn": 25,
    "animateLoading": true,
    "overflow": "NONE",
    "fontFamily": "Noto Sans",
    "parentColumnSpace": 2.3203125,
    "dynamicTriggerPathList": [],
    "leftColumn": 0,
    "dynamicBindingPathList": [
        {"key": "truncateButtonColor"},
        {"key": "borderRadius"}
    ],
    "shouldTruncate": false,
    "truncateButtonColor": "{{appsmith.theme.colors.primaryColor}}",
    "text": "BÀN GIAO KHÁCH HÀNG",
    "key": "sxe9xqxc8w",
    "isDeprecated": false,
    "rightColumn": 41,
    "textAlign": "LEFT",
    "dynamicHeight": "FIXED",
    "widgetId": "u85iw2swgp",
    "minWidth": 450,
    "isVisible": true,
    "fontStyle": "BOLD",
    "textColor": "#16a34a",
    "version": 1,
    "parentId": "lfhj92stre",
    "tags": [
        "Suggested",
        "Content"
    ],
    "renderMode": "CANVAS",
    "isLoading": false,
    "mobileTopRow": 1,
    "responsiveBehavior": "fill",
    "borderRadius": "{{appsmith.theme.borderRadius.appBorderRadius}}",
    "mobileLeftColumn": 9,
    "maxDynamicHeight": 9000,
    "fontSize": "2.0rem",
    "minDynamicHeight": 4
}